whosellm/__init__.py
whosellm/capabilities.py
whosellm/model_version.py
whosellm/provider.py
whosellm/py.typed
whosellm/models/__init__.py
whosellm/models/base.py
whosellm/models/config.py
whosellm/models/dynamic_enum.py
whosellm/models/patterns.py
whosellm/models/registry.py
whosellm/models/families/__init__.py
whosellm/models/families/alibaba.py
whosellm/models/families/anthropic.py
whosellm/models/families/gemini.py
whosellm/models/families/others.py
whosellm/models/families/vidu.py
whosellm/models/families/zhipu.py
whosellm/models/families/deepseek/__init__.py
whosellm/models/families/deepseek/deepseek_official.py
whosellm/models/families/deepseek/tencent.py
whosellm/models/families/openai/__init__.py
whosellm/models/families/openai/openai_gpt_3_5.py
whosellm/models/families/openai/openai_gpt_4.py
whosellm/models/families/openai/openai_gpt_4_1.py
whosellm/models/families/openai/openai_gpt_4o.py
whosellm/models/families/openai/openai_gpt_5.py
whosellm/models/families/openai/openai_gpt_5_1.py
whosellm/models/families/openai/openai_o1.py
whosellm/models/families/openai/openai_o3.py
whosellm/models/families/openai/openai_o4.py
whosellm-0.1.1a3.dist-info/METADATA
whosellm-0.1.1a3.dist-info/WHEEL
whosellm-0.1.1a3.dist-info/licenses/LICENSE
whosellm-0.1.1a3.dist-info/RECORD
