Metadata-Version: 2.4
Name: whosellm
Version: 0.1.1a3
Summary: A unified LLM model version and capability management library
Author-email: JQQ <jqq1716@gmail.com>
License: MIT
License-File: LICENSE
Requires-Python: <4.0,>=3.10
Requires-Dist: parse>=1.20.2
Requires-Dist: vrl-python<0.2.0,>=0.1.0
Provides-Extra: dev
Requires-Dist: bump-my-version>=0.30.0; extra == 'dev'
Requires-Dist: mypy<2.0.0,>=1.17.1; extra == 'dev'
Requires-Dist: poethepoet<0.38.0,>=0.37.0; extra == 'dev'
Requires-Dist: pytest<9.0.0,>=8.4.1; extra == 'dev'
Requires-Dist: ruff<0.13.0,>=0.12.9; extra == 'dev'
Provides-Extra: test
Requires-Dist: inline-snapshot<0.28.0,>=0.27.2; extra == 'test'
Requires-Dist: polyfactory<3.0.0,>=2.22.2; extra == 'test'
Requires-Dist: pytest-asyncio<2.0.0,>=1.1.0; extra == 'test'
Requires-Dist: pytest-cov<7.0.0,>=6.2.1; extra == 'test'
Requires-Dist: pytest-dotenv<0.6.0,>=0.5.2; extra == 'test'
Requires-Dist: pytest-mock<4.0.0,>=3.14.1; extra == 'test'
